pytest_ngrok/__init__.py
pytest_ngrok/django.py
pytest_ngrok/install.py
pytest_ngrok/manager.py
pytest_ngrok/plugin.py
pytest_ngrok-0.0.4.dist-info/LICENSE
pytest_ngrok-0.0.4.dist-info/METADATA
pytest_ngrok-0.0.4.dist-info/WHEEL
pytest_ngrok-0.0.4.dist-info/entry_points.txt
pytest_ngrok-0.0.4.dist-info/top_level.txt
pytest_ngrok-0.0.4.dist-info/RECORD
