Metadata-Version: 2.1
Name: pytest-ngrok
Version: 0.0.4
Summary: UNKNOWN
Home-page: https://github.com/Apkawa/pytest-ngrok
Author: Apkawa
Author-email: apkawa@gmail.com
License: MIT
Keywords: pytest
Platform: UNKNOWN
Classifier: Development Status :: 3 - Alpha
Classifier: Framework :: Pytest
Classifier: Intended Audience :: Developers
Classifier: Environment :: Web Environment
Classifier: License :: OSI Approved :: MIT License
Classifier: Programming Language :: Python
Classifier: Programming Language :: Python :: 3
Classifier: Programming Language :: Python :: 3.6
Classifier: Programming Language :: Python :: 3.7
Classifier: Programming Language :: Python :: 3.8
Classifier: Programming Language :: Python :: 3.9
Requires-Python: >=3.6, <4
License-File: LICENSE
Requires-Dist: pytest
